{
  "produto": [
    {
      "nome": "HOSSOMAKI MIX",
      "descricao": "Arroz envolto por alga recheado com ovo, pepino, kani, cenoura, alface e gengibre em conserva.",
      "url": "https://i.pinimg.com/originals/f1/36/1d/f1361d44b85af8cb92dee9fec51b05a0.png",
      "preco": "6.90",
      "id": 1
    },
    {
      "nome": "HOSSOMAKI MIX",
      "descricao": "Arroz envolto por alga recheado com ovo, pepino, kani, cenoura, alface e gengibre em conserva.",
      "url": "https://media.istockphoto.com/id/1367831478/pt/foto/japanese-food-combo-of-sushis-and-sahimis-in-black-background.jpg?b=1&s=170667a&w=0&k=20&c=B1BRrzHxcP21x4TsDW2M6a5E0fI5FiPmqFNhI5RGbCk=",
      "preco": "11.22",
      "id": 2
    },
    {
      "nome": "TEMAKI SALMÃO",
      "descricao": "Arroz cubos de salmão fresco, cogumelos shimeji, folhas de nori e cream cheese.",
      "url": "https://media.istockphoto.com/photos/temaki-salmon-oriental-meal-picture-id1407002631?b=1&k=20&m=1407002631&s=170667a&w=0&h=_kjJ4Tj0XHiauZEcVVjcZTspCsaf0emfqr5GzJ9B2Dw=",
      "preco": "21.50",
      "id": 3
    },
    {
      "nome": "HOT PHILADELPHIA (6 Unid.)",
      "descricao": "Empanado com alga, arroz, salmão, cream cheese e crispy de couve frita.",
      "url": "https://img.itdg.com.br/images/recipes/000/056/937/356433/356433_original.jpg",
      "preco": "17.90",
      "id": 4
    }
  ]
}
